converter/__init__.py
converter/input.xml
converter/main.py
converter/output.json
ssi_converter_thuongnn-0.1.0.dist-info/LICENSE
ssi_converter_thuongnn-0.1.0.dist-info/WHEEL
ssi_converter_thuongnn-0.1.0.dist-info/METADATA
ssi_converter_thuongnn-0.1.0.dist-info/RECORD
